{"layout":"indopak13_qudratullah","page":190,"lines":[{"line_type":"ayah","is_centered":false,"words":[{"word_index":18372,"word_key":"6:79","surah":6,"ayah":79,"text":"اَنَا","word_in_ayah":9},{"word_index":18373,"word_key":"6:79","surah":6,"ayah":79,"text":"مِنَ","word_in_ayah":10},{"word_index":18374,"word_key":"6:79","surah":6,"ayah":79,"text":"الْمُشْرِكِیْنَ","word_in_ayah":11},{"word_index":18375,"word_key":"6:79","surah":6,"ayah":79,"text":"۟ۚ","word_in_ayah":12},{"word_index":18376,"word_key":"6:80","surah":6,"ayah":80,"text":"وَحَآجَّهٗ","word_in_ayah":0},{"word_index":18377,"word_key":"6:80","surah":6,"ayah":80,"text":"قَوْمُهٗ ؕ","word_in_ayah":1},{"word_index":18378,"word_key":"6:80","surah":6,"ayah":80,"text":"قَالَ","word_in_ayah":2},{"word_index":18379,"word_key":"6:80","surah":6,"ayah":80,"text":"اَتُحَآجُّوْٓنِّیْ","word_in_ayah":3}]},{"line_type":"ayah","is_centered":false,"words":[{"word_index":18380,"word_key":"6:80","surah":6,"ayah":80,"text":"فِی","word_in_ayah":4},{"word_index":18381,"word_key":"6:80","surah":6,"ayah":80,"text":"اللّٰهِ","word_in_ayah":5},{"word_index":18382,"word_key":"6:80","surah":6,"ayah":80,"text":"وَقَدْ","word_in_ayah":6},{"word_index":18383,"word_key":"6:80","surah":6,"ayah":80,"text":"هَدٰىنِ ؕ","word_in_ayah":7},{"word_index":18384,"word_key":"6:80","surah":6,"ayah":80,"text":"وَلَاۤ","word_in_ayah":8},{"word_index":18385,"word_key":"6:80","surah":6,"ayah":80,"text":"اَخَافُ","word_in_ayah":9},{"word_index":18386,"word_key":"6:80","surah":6,"ayah":80,"text":"مَا","word_in_ayah":10},{"word_index":18387,"word_key":"6:80","surah":6,"ayah":80,"text":"تُشْرِكُوْنَ","word_in_ayah":11},{"word_index":18388,"word_key":"6:80","surah":6,"ayah":80,"text":"بِهٖۤ","word_in_ayah":12}]},{"line_type":"ayah","is_centered":false,"words":[{"word_index":18389,"word_key":"6:80","surah":6,"ayah":80,"text":"اِلَّاۤ","word_in_ayah":13},{"word_index":18390,"word_key":"6:80","surah":6,"ayah":80,"text":"اَنْ","word_in_ayah":14},{"word_index":18391,"word_key":"6:80","surah":6,"ayah":80,"text":"یَّشَآءَ","word_in_ayah":15},{"word_index":18392,"word_key":"6:80","surah":6,"ayah":80,"text":"رَبِّیْ","word_in_ayah":16},{"word_index":18393,"word_key":"6:80","surah":6,"ayah":80,"text":"شَیْـًٔا ؕ","word_in_ayah":17},{"word_index":18394,"word_key":"6:80","surah":6,"ayah":80,"text":"وَسِعَ","word_in_ayah":18},{"word_index":18395,"word_key":"6:80","surah":6,"ayah":80,"text":"رَبِّیْ","word_in_ayah":19},{"word_index":18396,"word_key":"6:80","surah":6,"ayah":80,"text":"كُلَّ","word_in_ayah":20},{"word_index":18397,"word_key":"6:80","surah":6,"ayah":80,"text":"شَیْءٍ","word_in_ayah":21},{"word_index":18398,"word_key":"6:80","surah":6,"ayah":80,"text":"عِلْمًا ؕ","word_in_ayah":22}]},{"line_type":"ayah","is_centered":false,"words":[{"word_index":18399,"word_key":"6:80","surah":6,"ayah":80,"text":"اَفَلَا","word_in_ayah":23},{"word_index":18400,"word_key":"6:80","surah":6,"ayah":80,"text":"تَتَذَكَّرُوْنَ","word_in_ayah":24},{"word_index":18401,"word_key":"6:80","surah":6,"ayah":80,"text":"۟","word_in_ayah":25},{"word_index":18402,"word_key":"6:81","surah":6,"ayah":81,"text":"وَكَیْفَ","word_in_ayah":0},{"word_index":18403,"word_key":"6:81","surah":6,"ayah":81,"text":"اَخَافُ","word_in_ayah":1},{"word_index":18404,"word_key":"6:81","surah":6,"ayah":81,"text":"مَاۤ","word_in_ayah":2},{"word_index":18405,"word_key":"6:81","surah":6,"ayah":81,"text":"اَشْرَكْتُمْ","word_in_ayah":3},{"word_index":18406,"word_key":"6:81","surah":6,"ayah":81,"text":"وَلَا","word_in_ayah":4}]},{"line_type":"ayah","is_centered":false,"words":[{"word_index":18407,"word_key":"6:81","surah":6,"ayah":81,"text":"تَخَافُوْنَ","word_in_ayah":5},{"word_index":18408,"word_key":"6:81","surah":6,"ayah":81,"text":"اَنَّكُمْ","word_in_ayah":6},{"word_index":18409,"word_key":"6:81","surah":6,"ayah":81,"text":"اَشْرَكْتُمْ","word_in_ayah":7},{"word_index":18410,"word_key":"6:81","surah":6,"ayah":81,"text":"بِاللّٰهِ","word_in_ayah":8},{"word_index":18411,"word_key":"6:81","surah":6,"ayah":81,"text":"مَا","word_in_ayah":9},{"word_index":18412,"word_key":"6:81","surah":6,"ayah":81,"text":"لَمْ","word_in_ayah":10},{"word_index":18413,"word_key":"6:81","surah":6,"ayah":81,"text":"یُنَزِّلْ","word_in_ayah":11},{"word_index":18414,"word_key":"6:81","surah":6,"ayah":81,"text":"بِهٖ","word_in_ayah":12}]},{"line_type":"ayah","is_centered":false,"words":[{"word_index":18415,"word_key":"6:81","surah":6,"ayah":81,"text":"عَلَیْكُمْ","word_in_ayah":13},{"word_index":18416,"word_key":"6:81","surah":6,"ayah":81,"text":"سُلْطٰنًا ؕ","word_in_ayah":14},{"word_index":18417,"word_key":"6:81","surah":6,"ayah":81,"text":"فَاَیُّ","word_in_ayah":15},{"word_index":18418,"word_key":"6:81","surah":6,"ayah":81,"text":"الْفَرِیْقَیْنِ","word_in_ayah":16},{"word_index":18419,"word_key":"6:81","surah":6,"ayah":81,"text":"اَحَقُّ","word_in_ayah":17},{"word_index":18420,"word_key":"6:81","surah":6,"ayah":81,"text":"بِالْاَمْنِ ۚ","word_in_ayah":18},{"word_index":18421,"word_key":"6:81","surah":6,"ayah":81,"text":"اِنْ","word_in_ayah":19}]},{"line_type":"ayah","is_centered":false,"words":[{"word_index":18422,"word_key":"6:81","surah":6,"ayah":81,"text":"كُنْتُمْ","word_in_ayah":20},{"word_index":18423,"word_key":"6:81","surah":6,"ayah":81,"text":"تَعْلَمُوْنَ","word_in_ayah":21},{"word_index":18424,"word_key":"6:81","surah":6,"ayah":81,"text":"۟ۘ","word_in_ayah":22},{"word_index":18425,"word_key":"6:82","surah":6,"ayah":82,"text":"اَلَّذِیْنَ","word_in_ayah":0},{"word_index":18426,"word_key":"6:82","surah":6,"ayah":82,"text":"اٰمَنُوْا","word_in_ayah":1},{"word_index":18427,"word_key":"6:82","surah":6,"ayah":82,"text":"وَلَمْ","word_in_ayah":2},{"word_index":18428,"word_key":"6:82","surah":6,"ayah":82,"text":"یَلْبِسُوْۤا","word_in_ayah":3},{"word_index":18429,"word_key":"6:82","surah":6,"ayah":82,"text":"اِیْمَانَهُمْ","word_in_ayah":4}]},{"line_type":"ayah","is_centered":false,"words":[{"word_index":18430,"word_key":"6:82","surah":6,"ayah":82,"text":"بِظُلْمٍ","word_in_ayah":5},{"word_index":18431,"word_key":"6:82","surah":6,"ayah":82,"text":"اُولٰٓىِٕكَ","word_in_ayah":6},{"word_index":18432,"word_key":"6:82","surah":6,"ayah":82,"text":"لَهُمُ","word_in_ayah":7},{"word_index":18433,"word_key":"6:82","surah":6,"ayah":82,"text":"الْاَمْنُ","word_in_ayah":8},{"word_index":18434,"word_key":"6:82","surah":6,"ayah":82,"text":"وَهُمْ","word_in_ayah":9},{"word_index":18435,"word_key":"6:82","surah":6,"ayah":82,"text":"مُّهْتَدُوْنَ","word_in_ayah":10},{"word_index":18436,"word_key":"6:82","surah":6,"ayah":82,"text":"۟۠","word_in_ayah":11},{"word_index":18437,"word_key":"6:83","surah":6,"ayah":83,"text":"وَتِلْكَ","word_in_ayah":0}]},{"line_type":"ayah","is_centered":false,"words":[{"word_index":18438,"word_key":"6:83","surah":6,"ayah":83,"text":"حُجَّتُنَاۤ","word_in_ayah":1},{"word_index":18439,"word_key":"6:83","surah":6,"ayah":83,"text":"اٰتَیْنٰهَاۤ","word_in_ayah":2},{"word_index":18440,"word_key":"6:83","surah":6,"ayah":83,"text":"اِبْرٰهِیْمَ","word_in_ayah":3},{"word_index":18441,"word_key":"6:83","surah":6,"ayah":83,"text":"عَلٰی","word_in_ayah":4},{"word_index":18442,"word_key":"6:83","surah":6,"ayah":83,"text":"قَوْمِهٖ ؕ","word_in_ayah":5},{"word_index":18443,"word_key":"6:83","surah":6,"ayah":83,"text":"نَرْفَعُ","word_in_ayah":6},{"word_index":18444,"word_key":"6:83","surah":6,"ayah":83,"text":"دَرَجٰتٍ","word_in_ayah":7}]},{"line_type":"ayah","is_centered":false,"words":[{"word_index":18445,"word_key":"6:83","surah":6,"ayah":83,"text":"مَّنْ","word_in_ayah":8},{"word_index":18446,"word_key":"6:83","surah":6,"ayah":83,"text":"نَّشَآءُ ؕ","word_in_ayah":9},{"word_index":18447,"word_key":"6:83","surah":6,"ayah":83,"text":"اِنَّ","word_in_ayah":10},{"word_index":18448,"word_key":"6:83","surah":6,"ayah":83,"text":"رَبَّكَ","word_in_ayah":11},{"word_index":18449,"word_key":"6:83","surah":6,"ayah":83,"text":"حَكِیْمٌ","word_in_ayah":12},{"word_index":18450,"word_key":"6:83","surah":6,"ayah":83,"text":"عَلِیْمٌ","word_in_ayah":13},{"word_index":18451,"word_key":"6:83","surah":6,"ayah":83,"text":"۟","word_in_ayah":14},{"word_index":18452,"word_key":"6:84","surah":6,"ayah":84,"text":"وَوَهَبْنَا","word_in_ayah":0},{"word_index":18453,"word_key":"6:84","surah":6,"ayah":84,"text":"لَهٗۤ","word_in_ayah":1}]},{"line_type":"ayah","is_centered":false,"words":[{"word_index":18454,"word_key":"6:84","surah":6,"ayah":84,"text":"اِسْحٰقَ","word_in_ayah":2},{"word_index":18455,"word_key":"6:84","surah":6,"ayah":84,"text":"وَیَعْقُوْبَ ؕ","word_in_ayah":3},{"word_index":18456,"word_key":"6:84","surah":6,"ayah":84,"text":"كُلًّا","word_in_ayah":4},{"word_index":18457,"word_key":"6:84","surah":6,"ayah":84,"text":"هَدَیْنَا ۚ","word_in_ayah":5},{"word_index":18458,"word_key":"6:84","surah":6,"ayah":84,"text":"وَنُوْحًا","word_in_ayah":6},{"word_index":18459,"word_key":"6:84","surah":6,"ayah":84,"text":"هَدَیْنَا","word_in_ayah":7},{"word_index":18460,"word_key":"6:84","surah":6,"ayah":84,"text":"مِنْ","word_in_ayah":8}]},{"line_type":"ayah","is_centered":false,"words":[{"word_index":18461,"word_key":"6:84","surah":6,"ayah":84,"text":"قَبْلُ","word_in_ayah":9},{"word_index":18462,"word_key":"6:84","surah":6,"ayah":84,"text":"وَمِنْ","word_in_ayah":10},{"word_index":18463,"word_key":"6:84","surah":6,"ayah":84,"text":"ذُرِّیَّتِهٖ","word_in_ayah":11},{"word_index":18464,"word_key":"6:84","surah":6,"ayah":84,"text":"دَاوٗدَ","word_in_ayah":12},{"word_index":18465,"word_key":"6:84","surah":6,"ayah":84,"text":"وَسُلَیْمٰنَ","word_in_ayah":13},{"word_index":18466,"word_key":"6:84","surah":6,"ayah":84,"text":"وَاَیُّوْبَ","word_in_ayah":14},{"word_index":18467,"word_key":"6:84","surah":6,"ayah":84,"text":"وَیُوْسُفَ","word_in_ayah":15}]},{"line_type":"ayah","is_centered":false,"words":[{"word_index":18468,"word_key":"6:84","surah":6,"ayah":84,"text":"وَمُوْسٰی","word_in_ayah":16},{"word_index":18469,"word_key":"6:84","surah":6,"ayah":84,"text":"وَهٰرُوْنَ ؕ","word_in_ayah":17},{"word_index":18470,"word_key":"6:84","surah":6,"ayah":84,"text":"وَكَذٰلِكَ","word_in_ayah":18},{"word_index":18471,"word_key":"6:84","surah":6,"ayah":84,"text":"نَجْزِی","word_in_ayah":19},{"word_index":18472,"word_key":"6:84","surah":6,"ayah":84,"text":"الْمُحْسِنِیْنَ","word_in_ayah":20},{"word_index":18473,"word_key":"6:84","surah":6,"ayah":84,"text":"۟ۙ","word_in_ayah":21}]}]}