{"layout":"indopak13_qudratullah","page":759,"lines":[{"line_type":"ayah","is_centered":false,"words":[{"word_index":75235,"word_key":"58:12","surah":58,"ayah":12,"text":"اٰمَنُوْۤا","word_in_ayah":2},{"word_index":75236,"word_key":"58:12","surah":58,"ayah":12,"text":"اِذَا","word_in_ayah":3},{"word_index":75237,"word_key":"58:12","surah":58,"ayah":12,"text":"نَاجَیْتُمُ","word_in_ayah":4},{"word_index":75238,"word_key":"58:12","surah":58,"ayah":12,"text":"الرَّسُوْلَ","word_in_ayah":5},{"word_index":75239,"word_key":"58:12","surah":58,"ayah":12,"text":"فَقَدِّمُوْا","word_in_ayah":6},{"word_index":75240,"word_key":"58:12","surah":58,"ayah":12,"text":"بَیْنَ","word_in_ayah":7},{"word_index":75241,"word_key":"58:12","surah":58,"ayah":12,"text":"یَدَیْ","word_in_ayah":8}]},{"line_type":"ayah","is_centered":false,"words":[{"word_index":75242,"word_key":"58:12","surah":58,"ayah":12,"text":"نَجْوٰىكُمْ","word_in_ayah":9},{"word_index":75243,"word_key":"58:12","surah":58,"ayah":12,"text":"صَدَقَةً ؕ","word_in_ayah":10},{"word_index":75244,"word_key":"58:12","surah":58,"ayah":12,"text":"ذٰلِكَ","word_in_ayah":11},{"word_index":75245,"word_key":"58:12","surah":58,"ayah":12,"text":"خَیْرٌ","word_in_ayah":12},{"word_index":75246,"word_key":"58:12","surah":58,"ayah":12,"text":"لَّكُمْ","word_in_ayah":13},{"word_index":75247,"word_key":"58:12","surah":58,"ayah":12,"text":"وَاَطْهَرُ ؕ","word_in_ayah":14},{"word_index":75248,"word_key":"58:12","surah":58,"ayah":12,"text":"فَاِنْ","word_in_ayah":15}]},{"line_type":"ayah","is_centered":false,"words":[{"word_index":75249,"word_key":"58:12","surah":58,"ayah":12,"text":"لَّمْ","word_in_ayah":16},{"word_index":75250,"word_key":"58:12","surah":58,"ayah":12,"text":"تَجِدُوْا","word_in_ayah":17},{"word_index":75251,"word_key":"58:12","surah":58,"ayah":12,"text":"فَاِنَّ","word_in_ayah":18},{"word_index":75252,"word_key":"58:12","surah":58,"ayah":12,"text":"اللّٰهَ","word_in_ayah":19},{"word_index":75253,"word_key":"58:12","surah":58,"ayah":12,"text":"غَفُوْرٌ","word_in_ayah":20},{"word_index":75254,"word_key":"58:12","surah":58,"ayah":12,"text":"رَّحِیْمٌ","word_in_ayah":21},{"word_index":75255,"word_key":"58:12","surah":58,"ayah":12,"text":"۟","word_in_ayah":22},{"word_index":75256,"word_key":"58:13","surah":58,"ayah":13,"text":"ءَاَشْفَقْتُمْ","word_in_ayah":0}]},{"line_type":"ayah","is_centered":false,"words":[{"word_index":75257,"word_key":"58:13","surah":58,"ayah":13,"text":"اَنْ","word_in_ayah":1},{"word_index":75258,"word_key":"58:13","surah":58,"ayah":13,"text":"تُقَدِّمُوْا","word_in_ayah":2},{"word_index":75259,"word_key":"58:13","surah":58,"ayah":13,"text":"بَیْنَ","word_in_ayah":3},{"word_index":75260,"word_key":"58:13","surah":58,"ayah":13,"text":"یَدَیْ","word_in_ayah":4},{"word_index":75261,"word_key":"58:13","surah":58,"ayah":13,"text":"نَجْوٰىكُمْ","word_in_ayah":5},{"word_index":75262,"word_key":"58:13","surah":58,"ayah":13,"text":"صَدَقٰتٍ ؕ","word_in_ayah":6},{"word_index":75263,"word_key":"58:13","surah":58,"ayah":13,"text":"فَاِذْ","word_in_ayah":7},{"word_index":75264,"word_key":"58:13","surah":58,"ayah":13,"text":"لَمْ","word_in_ayah":8}]},{"line_type":"ayah","is_centered":false,"words":[{"word_index":75265,"word_key":"58:13","surah":58,"ayah":13,"text":"تَفْعَلُوْا","word_in_ayah":9},{"word_index":75266,"word_key":"58:13","surah":58,"ayah":13,"text":"وَتَابَ","word_in_ayah":10},{"word_index":75267,"word_key":"58:13","surah":58,"ayah":13,"text":"اللّٰهُ","word_in_ayah":11},{"word_index":75268,"word_key":"58:13","surah":58,"ayah":13,"text":"عَلَیْكُمْ","word_in_ayah":12},{"word_index":75269,"word_key":"58:13","surah":58,"ayah":13,"text":"فَاَقِیْمُوا","word_in_ayah":13},{"word_index":75270,"word_key":"58:13","surah":58,"ayah":13,"text":"الصَّلٰوةَ","word_in_ayah":14},{"word_index":75271,"word_key":"58:13","surah":58,"ayah":13,"text":"وَاٰتُوا","word_in_ayah":15}]},{"line_type":"ayah","is_centered":false,"words":[{"word_index":75272,"word_key":"58:13","surah":58,"ayah":13,"text":"الزَّكٰوةَ","word_in_ayah":16},{"word_index":75273,"word_key":"58:13","surah":58,"ayah":13,"text":"وَاَطِیْعُوا","word_in_ayah":17},{"word_index":75274,"word_key":"58:13","surah":58,"ayah":13,"text":"اللّٰهَ","word_in_ayah":18},{"word_index":75275,"word_key":"58:13","surah":58,"ayah":13,"text":"وَرَسُوْلَهٗ ؕ","word_in_ayah":19},{"word_index":75276,"word_key":"58:13","surah":58,"ayah":13,"text":"وَاللّٰهُ","word_in_ayah":20},{"word_index":75277,"word_key":"58:13","surah":58,"ayah":13,"text":"خَبِیْرٌ","word_in_ayah":21},{"word_index":75278,"word_key":"58:13","surah":58,"ayah":13,"text":"بِمَا","word_in_ayah":22}]},{"line_type":"ayah","is_centered":false,"words":[{"word_index":75279,"word_key":"58:13","surah":58,"ayah":13,"text":"تَعْمَلُوْنَ","word_in_ayah":23},{"word_index":75280,"word_key":"58:13","surah":58,"ayah":13,"text":"۟۠","word_in_ayah":24},{"word_index":75281,"word_key":"58:14","surah":58,"ayah":14,"text":"اَلَمْ","word_in_ayah":0},{"word_index":75282,"word_key":"58:14","surah":58,"ayah":14,"text":"تَرَ","word_in_ayah":1},{"word_index":75283,"word_key":"58:14","surah":58,"ayah":14,"text":"اِلَی","word_in_ayah":2},{"word_index":75284,"word_key":"58:14","surah":58,"ayah":14,"text":"الَّذِیْنَ","word_in_ayah":3},{"word_index":75285,"word_key":"58:14","surah":58,"ayah":14,"text":"تَوَلَّوْا","word_in_ayah":4},{"word_index":75286,"word_key":"58:14","surah":58,"ayah":14,"text":"قَوْمًا","word_in_ayah":5},{"word_index":75287,"word_key":"58:14","surah":58,"ayah":14,"text":"غَضِبَ","word_in_ayah":6}]},{"line_type":"ayah","is_centered":false,"words":[{"word_index":75288,"word_key":"58:14","surah":58,"ayah":14,"text":"اللّٰهُ","word_in_ayah":7},{"word_index":75289,"word_key":"58:14","surah":58,"ayah":14,"text":"عَلَیْهِمْ ؕ","word_in_ayah":8},{"word_index":75290,"word_key":"58:14","surah":58,"ayah":14,"text":"مَا","word_in_ayah":9},{"word_index":75291,"word_key":"58:14","surah":58,"ayah":14,"text":"هُمْ","word_in_ayah":10},{"word_index":75292,"word_key":"58:14","surah":58,"ayah":14,"text":"مِّنْكُمْ","word_in_ayah":11},{"word_index":75293,"word_key":"58:14","surah":58,"ayah":14,"text":"وَلَا","word_in_ayah":12},{"word_index":75294,"word_key":"58:14","surah":58,"ayah":14,"text":"مِنْهُمْ ۙ","word_in_ayah":13},{"word_index":75295,"word_key":"58:14","surah":58,"ayah":14,"text":"وَیَحْلِفُوْنَ","word_in_ayah":14}]},{"line_type":"ayah","is_centered":false,"words":[{"word_index":75296,"word_key":"58:14","surah":58,"ayah":14,"text":"عَلَی","word_in_ayah":15},{"word_index":75297,"word_key":"58:14","surah":58,"ayah":14,"text":"الْكَذِبِ","word_in_ayah":16},{"word_index":75298,"word_key":"58:14","surah":58,"ayah":14,"text":"وَهُمْ","word_in_ayah":17},{"word_index":75299,"word_key":"58:14","surah":58,"ayah":14,"text":"یَعْلَمُوْنَ","word_in_ayah":18},{"word_index":75300,"word_key":"58:14","surah":58,"ayah":14,"text":"۟ۚ","word_in_ayah":19},{"word_index":75301,"word_key":"58:15","surah":58,"ayah":15,"text":"اَعَدَّ","word_in_ayah":0},{"word_index":75302,"word_key":"58:15","surah":58,"ayah":15,"text":"اللّٰهُ","word_in_ayah":1},{"word_index":75303,"word_key":"58:15","surah":58,"ayah":15,"text":"لَهُمْ","word_in_ayah":2}]},{"line_type":"ayah","is_centered":false,"words":[{"word_index":75304,"word_key":"58:15","surah":58,"ayah":15,"text":"عَذَابًا","word_in_ayah":3},{"word_index":75305,"word_key":"58:15","surah":58,"ayah":15,"text":"شَدِیْدًا ؕ","word_in_ayah":4},{"word_index":75306,"word_key":"58:15","surah":58,"ayah":15,"text":"اِنَّهُمْ","word_in_ayah":5},{"word_index":75307,"word_key":"58:15","surah":58,"ayah":15,"text":"سَآءَ","word_in_ayah":6},{"word_index":75308,"word_key":"58:15","surah":58,"ayah":15,"text":"مَا","word_in_ayah":7},{"word_index":75309,"word_key":"58:15","surah":58,"ayah":15,"text":"كَانُوْا","word_in_ayah":8},{"word_index":75310,"word_key":"58:15","surah":58,"ayah":15,"text":"یَعْمَلُوْنَ","word_in_ayah":9},{"word_index":75311,"word_key":"58:15","surah":58,"ayah":15,"text":"۟","word_in_ayah":10}]},{"line_type":"ayah","is_centered":false,"words":[{"word_index":75312,"word_key":"58:16","surah":58,"ayah":16,"text":"اِتَّخَذُوْۤا","word_in_ayah":0},{"word_index":75313,"word_key":"58:16","surah":58,"ayah":16,"text":"اَیْمَانَهُمْ","word_in_ayah":1},{"word_index":75314,"word_key":"58:16","surah":58,"ayah":16,"text":"جُنَّةً","word_in_ayah":2},{"word_index":75315,"word_key":"58:16","surah":58,"ayah":16,"text":"فَصَدُّوْا","word_in_ayah":3},{"word_index":75316,"word_key":"58:16","surah":58,"ayah":16,"text":"عَنْ","word_in_ayah":4},{"word_index":75317,"word_key":"58:16","surah":58,"ayah":16,"text":"سَبِیْلِ","word_in_ayah":5},{"word_index":75318,"word_key":"58:16","surah":58,"ayah":16,"text":"اللّٰهِ","word_in_ayah":6}]},{"line_type":"ayah","is_centered":false,"words":[{"word_index":75319,"word_key":"58:16","surah":58,"ayah":16,"text":"فَلَهُمْ","word_in_ayah":7},{"word_index":75320,"word_key":"58:16","surah":58,"ayah":16,"text":"عَذَابٌ","word_in_ayah":8},{"word_index":75321,"word_key":"58:16","surah":58,"ayah":16,"text":"مُّهِیْنٌ","word_in_ayah":9},{"word_index":75322,"word_key":"58:16","surah":58,"ayah":16,"text":"۟","word_in_ayah":10},{"word_index":75323,"word_key":"58:17","surah":58,"ayah":17,"text":"لَنْ","word_in_ayah":0},{"word_index":75324,"word_key":"58:17","surah":58,"ayah":17,"text":"تُغْنِیَ","word_in_ayah":1},{"word_index":75325,"word_key":"58:17","surah":58,"ayah":17,"text":"عَنْهُمْ","word_in_ayah":2},{"word_index":75326,"word_key":"58:17","surah":58,"ayah":17,"text":"اَمْوَالُهُمْ","word_in_ayah":3}]},{"line_type":"ayah","is_centered":false,"words":[{"word_index":75327,"word_key":"58:17","surah":58,"ayah":17,"text":"وَلَاۤ","word_in_ayah":4},{"word_index":75328,"word_key":"58:17","surah":58,"ayah":17,"text":"اَوْلَادُهُمْ","word_in_ayah":5},{"word_index":75329,"word_key":"58:17","surah":58,"ayah":17,"text":"مِّنَ","word_in_ayah":6},{"word_index":75330,"word_key":"58:17","surah":58,"ayah":17,"text":"اللّٰهِ","word_in_ayah":7},{"word_index":75331,"word_key":"58:17","surah":58,"ayah":17,"text":"شَیْـًٔا ؕ","word_in_ayah":8},{"word_index":75332,"word_key":"58:17","surah":58,"ayah":17,"text":"اُولٰٓىِٕكَ","word_in_ayah":9},{"word_index":75333,"word_key":"58:17","surah":58,"ayah":17,"text":"اَصْحٰبُ","word_in_ayah":10},{"word_index":75334,"word_key":"58:17","surah":58,"ayah":17,"text":"النَّارِ ؕ","word_in_ayah":11}]}]}