{
  "audio_file": {
    "id": 0,
    "chapter_id": 105,
    "audio_url": "audio/alafasy/recitation/105.mp3",
    "timestamps": [
      {
        "verse_key": "105:1",
        "timestamp_from": 0,
        "timestamp_to": 8050,
        "duration": 8050,
        "segments": [
          [
            1,
            60.0,
            541.0
          ],
          [
            2,
            661.0,
            1020.0
          ],
          [
            3,
            1121.0,
            1642.0
          ],
          [
            4,
            1762.0,
            2343.0
          ],
          [
            5,
            2443.0,
            3224.0
          ],
          [
            6,
            3324.0,
            4526.0
          ],
          [
            7,
            4646.0,
            6901.0
          ]
        ]
      },
      {
        "verse_key": "105:2",
        "timestamp_from": 8050,
        "timestamp_to": 14306,
        "duration": 6256,
        "segments": [
          [
            1,
            8070.0,
            8571.0
          ],
          [
            2,
            8652.0,
            9393.0
          ],
          [
            3,
            9494.0,
            10456.0
          ],
          [
            4,
            10556.0,
            10857.0
          ],
          [
            5,
            10998.0,
            13363.0
          ]
        ]
      },
      {
        "verse_key": "105:3",
        "timestamp_from": 14306,
        "timestamp_to": 21153,
        "duration": 6847,
        "segments": [
          [
            1,
            14366.0,
            15307.0
          ],
          [
            2,
            15407.0,
            16288.0
          ],
          [
            3,
            16408.0,
            17149.0
          ],
          [
            4,
            17249.0,
            21153.0
          ]
        ]
      },
      {
        "verse_key": "105:4",
        "timestamp_from": 21153,
        "timestamp_to": 30473,
        "duration": 9320,
        "segments": [
          [
            1,
            21153.0,
            23217.0
          ],
          [
            2,
            23298.0,
            25021.0
          ],
          [
            3,
            25703.0,
            26705.0
          ],
          [
            4,
            26825.0,
            30493.0
          ]
        ]
      },
      {
        "verse_key": "105:5",
        "timestamp_from": 30473,
        "timestamp_to": 39424,
        "duration": 8951,
        "segments": [
          [
            1,
            30493.0,
            31634.0
          ],
          [
            2,
            31735.0,
            32736.0
          ],
          [
            3,
            33917.0,
            39424.0
          ]
        ]
      }
    ]
  }
}