{
    "audio_file":  {
                       "id":  0,
                       "chapter_id":  76,
                       "audio_url":  "audio/alafasy/recitation/76.mp3",
                       "timestamps":  [
                                          {
                                              "verse_key":  "76:1",
                                              "timestamp_from":  0,
                                              "timestamp_to":  9880,
                                              "duration":  9880,
                                              "segments":  [
                                                               1,
                                                               50,
                                                               370,
                                                               2,
                                                               380,
                                                               850,
                                                               3,
                                                               860,
                                                               1480,
                                                               4,
                                                               1490,
                                                               3100,
                                                               5,
                                                               3110,
                                                               4700,
                                                               6,
                                                               4710,
                                                               4980,
                                                               7,
                                                               4990,
                                                               5790,
                                                               8,
                                                               5800,
                                                               6110,
                                                               9,
                                                               6120,
                                                               7270,
                                                               10,
                                                               7280,
                                                               7960,
                                                               11,
                                                               7970,
                                                               9880
                                                           ]
                                          },
                                          {
                                              "verse_key":  "76:2",
                                              "timestamp_from":  9880,
                                              "timestamp_to":  22870,
                                              "duration":  12990,
                                              "segments":  [
                                                               1,
                                                               9910,
                                                               11320,
                                                               2,
                                                               11330,
                                                               12140,
                                                               3,
                                                               12150,
                                                               14020,
                                                               4,
                                                               14030,
                                                               14880,
                                                               5,
                                                               14890,
                                                               15780,
                                                               6,
                                                               15790,
                                                               17170,
                                                               7,
                                                               17180,
                                                               18670,
                                                               8,
                                                               18680,
                                                               20060,
                                                               9,
                                                               20070,
                                                               21740,
                                                               10,
                                                               21750,
                                                               22870
                                                           ]
                                          },
                                          {
                                              "verse_key":  "76:3",
                                              "timestamp_from":  22870,
                                              "timestamp_to":  32480,
                                              "duration":  9610,
                                              "segments":  [
                                                               1,
                                                               22900,
                                                               24280,
                                                               2,
                                                               24290,
                                                               25430,
                                                               3,
                                                               25440,
                                                               26350,
                                                               4,
                                                               26360,
                                                               27990,
                                                               5,
                                                               28000,
                                                               28800,
                                                               6,
                                                               28810,
                                                               31250,
                                                               7,
                                                               31260,
                                                               32480
                                                           ]
                                          },
                                          {
                                              "verse_key":  "76:4",
                                              "timestamp_from":  32480,
                                              "timestamp_to":  41850,
                                              "duration":  9370,
                                              "segments":  [
                                                               1,
                                                               32510,
                                                               34910,
                                                               2,
                                                               34920,
                                                               36120,
                                                               3,
                                                               36130,
                                                               37600,
                                                               4,
                                                               37610,
                                                               38640,
                                                               5,
                                                               38650,
                                                               39740,
                                                               6,
                                                               39750,
                                                               41850
                                                           ]
                                          },
                                          {
                                              "verse_key":  "76:5",
                                              "timestamp_from":  41850,
                                              "timestamp_to":  51040,
                                              "duration":  9190,
                                              "segments":  [
                                                               1,
                                                               41880,
                                                               43050,
                                                               2,
                                                               43060,
                                                               44260,
                                                               3,
                                                               44270,
                                                               45360,
                                                               4,
                                                               45370,
                                                               46440,
                                                               5,
                                                               46450,
                                                               47790,
                                                               6,
                                                               47800,
                                                               48490,
                                                               7,
                                                               48500,
                                                               49640,
                                                               8,
                                                               49650,
                                                               51040
                                                           ]
                                          },
                                          {
                                              "verse_key":  "76:6",
                                              "timestamp_from":  51040,
                                              "timestamp_to":  58730,
                                              "duration":  7690,
                                              "segments":  [
                                                               1,
                                                               51120,
                                                               52600,
                                                               2,
                                                               52610,
                                                               53370,
                                                               3,
                                                               53380,
                                                               53930,
                                                               4,
                                                               53940,
                                                               54800,
                                                               5,
                                                               54810,
                                                               55530,
                                                               6,
                                                               55540,
                                                               57340,
                                                               7,
                                                               57350,
                                                               58730
                                                           ]
                                          },
                                          {
                                              "verse_key":  "76:7",
                                              "timestamp_from":  58730,
                                              "timestamp_to":  67370,
                                              "duration":  8640,
                                              "segments":  [
                                                               1,
                                                               58770,
                                                               59670,
                                                               2,
                                                               59680,
                                                               61330,
                                                               3,
                                                               61340,
                                                               62630,
                                                               4,
                                                               62640,
                                                               63150,
                                                               5,
                                                               63160,
                                                               64770,
                                                               6,
                                                               64780,
                                                               65820,
                                                               7,
                                                               65830,
                                                               67370
                                                           ]
                                          },
                                          {
                                              "verse_key":  "76:8",
                                              "timestamp_from":  67370,
                                              "timestamp_to":  76450,
                                              "duration":  9080,
                                              "segments":  [
                                                               1,
                                                               67400,
                                                               68730,
                                                               2,
                                                               68740,
                                                               69630,
                                                               3,
                                                               69640,
                                                               70250,
                                                               4,
                                                               70260,
                                                               71290,
                                                               5,
                                                               71300,
                                                               72210,
                                                               6,
                                                               72220,
                                                               74300,
                                                               7,
                                                               74310,
                                                               76450
                                                           ]
                                          },
                                          {
                                              "verse_key":  "76:9",
                                              "timestamp_from":  76450,
                                              "timestamp_to":  87650,
                                              "duration":  11200,
                                              "segments":  [
                                                               1,
                                                               76480,
                                                               78100,
                                                               2,
                                                               78110,
                                                               79210,
                                                               3,
                                                               79220,
                                                               80050,
                                                               4,
                                                               80060,
                                                               80830,
                                                               5,
                                                               80840,
                                                               81190,
                                                               6,
                                                               81200,
                                                               81950,
                                                               7,
                                                               81960,
                                                               83240,
                                                               8,
                                                               83250,
                                                               85350,
                                                               9,
                                                               85360,
                                                               86430,
                                                               10,
                                                               86440,
                                                               87650
                                                           ]
                                          },
                                          {
                                              "verse_key":  "76:10",
                                              "timestamp_from":  87650,
                                              "timestamp_to":  94960,
                                              "duration":  7310,
                                              "segments":  [
                                                               1,
                                                               87680,
                                                               88980,
                                                               2,
                                                               88990,
                                                               89790,
                                                               3,
                                                               89800,
                                                               89890,
                                                               4,
                                                               89900,
                                                               91070,
                                                               5,
                                                               91080,
                                                               91810,
                                                               6,
                                                               91820,
                                                               92610,
                                                               7,
                                                               92620,
                                                               94960
                                                           ]
                                          },
                                          {
                                              "verse_key":  "76:11",
                                              "timestamp_from":  94960,
                                              "timestamp_to":  103530,
                                              "duration":  8570,
                                              "segments":  [
                                                               1,
                                                               94990,
                                                               96070,
                                                               2,
                                                               96080,
                                                               96820,
                                                               3,
                                                               96830,
                                                               97470,
                                                               4,
                                                               97480,
                                                               98260,
                                                               5,
                                                               98270,
                                                               99070,
                                                               6,
                                                               99080,
                                                               100330,
                                                               7,
                                                               100340,
                                                               101350,
                                                               8,
                                                               101360,
                                                               103530
                                                           ]
                                          },
                                          {
                                              "verse_key":  "76:12",
                                              "timestamp_from":  103530,
                                              "timestamp_to":  109980,
                                              "duration":  6450,
                                              "segments":  [
                                                               1,
                                                               103560,
                                                               105120,
                                                               2,
                                                               105130,
                                                               105650,
                                                               3,
                                                               105660,
                                                               106450,
                                                               4,
                                                               106460,
                                                               107960,
                                                               5,
                                                               107970,
                                                               109980
                                                           ]
                                          },
                                          {
                                              "verse_key":  "76:13",
                                              "timestamp_from":  109980,
                                              "timestamp_to":  120650,
                                              "duration":  10670,
                                              "segments":  [
                                                               1,
                                                               110030,
                                                               111250,
                                                               2,
                                                               111260,
                                                               111950,
                                                               3,
                                                               111960,
                                                               112390,
                                                               4,
                                                               112400,
                                                               115470,
                                                               5,
                                                               115480,
                                                               115800,
                                                               6,
                                                               115810,
                                                               116540,
                                                               7,
                                                               116550,
                                                               117300,
                                                               8,
                                                               117310,
                                                               117930,
                                                               9,
                                                               117940,
                                                               119120,
                                                               10,
                                                               119130,
                                                               120650
                                                           ]
                                          },
                                          {
                                              "verse_key":  "76:14",
                                              "timestamp_from":  120650,
                                              "timestamp_to":  127730,
                                              "duration":  7080,
                                              "segments":  [
                                                               1,
                                                               120680,
                                                               121930,
                                                               2,
                                                               121940,
                                                               122910,
                                                               3,
                                                               122920,
                                                               124070,
                                                               4,
                                                               124080,
                                                               125180,
                                                               5,
                                                               125190,
                                                               126410,
                                                               6,
                                                               126420,
                                                               127730
                                                           ]
                                          },
                                          {
                                              "verse_key":  "76:15",
                                              "timestamp_from":  127730,
                                              "timestamp_to":  138620,
                                              "duration":  10890,
                                              "segments":  [
                                                               1,
                                                               127760,
                                                               128670,
                                                               2,
                                                               128680,
                                                               130400,
                                                               3,
                                                               130410,
                                                               132360,
                                                               4,
                                                               132370,
                                                               133220,
                                                               5,
                                                               133230,
                                                               134170,
                                                               6,
                                                               134180,
                                                               136340,
                                                               7,
                                                               136350,
                                                               137140,
                                                               8,
                                                               137150,
                                                               138620
                                                           ]
                                          },
                                          {
                                              "verse_key":  "76:16",
                                              "timestamp_from":  138620,
                                              "timestamp_to":  145260,
                                              "duration":  6640,
                                              "segments":  [
                                                               1,
                                                               138650,
                                                               139780,
                                                               2,
                                                               139790,
                                                               140710,
                                                               3,
                                                               140720,
                                                               142990,
                                                               4,
                                                               143000,
                                                               143860,
                                                               5,
                                                               143870,
                                                               145260
                                                           ]
                                          },
                                          {
                                              "verse_key":  "76:17",
                                              "timestamp_from":  145260,
                                              "timestamp_to":  152440,
                                              "duration":  7180,
                                              "segments":  [
                                                               1,
                                                               145290,
                                                               146320,
                                                               2,
                                                               146330,
                                                               147080,
                                                               3,
                                                               147090,
                                                               147640,
                                                               4,
                                                               147650,
                                                               149100,
                                                               5,
                                                               149110,
                                                               150290,
                                                               6,
                                                               150300,
                                                               152440
                                                           ]
                                          },
                                          {
                                              "verse_key":  "76:18",
                                              "timestamp_from":  152440,
                                              "timestamp_to":  157590,
                                              "duration":  5150,
                                              "segments":  [
                                                               1,
                                                               152470,
                                                               153920,
                                                               2,
                                                               153930,
                                                               154690,
                                                               3,
                                                               154700,
                                                               156100,
                                                               4,
                                                               156110,
                                                               157590
                                                           ]
                                          },
                                          {
                                              "verse_key":  "76:19",
                                              "timestamp_from":  157590,
                                              "timestamp_to":  168700,
                                              "duration":  11110,
                                              "segments":  [
                                                               1,
                                                               157620,
                                                               158470,
                                                               2,
                                                               158480,
                                                               159470,
                                                               3,
                                                               159480,
                                                               161340,
                                                               4,
                                                               161350,
                                                               162540,
                                                               5,
                                                               162550,
                                                               163070,
                                                               6,
                                                               163080,
                                                               164180,
                                                               7,
                                                               164190,
                                                               165340,
                                                               8,
                                                               165350,
                                                               166130,
                                                               9,
                                                               166140,
                                                               168700
                                                           ]
                                          },
                                          {
                                              "verse_key":  "76:20",
                                              "timestamp_from":  168700,
                                              "timestamp_to":  176000,
                                              "duration":  7300,
                                              "segments":  [
                                                               1,
                                                               168730,
                                                               169400,
                                                               2,
                                                               169410,
                                                               170180,
                                                               3,
                                                               170190,
                                                               171260,
                                                               4,
                                                               171270,
                                                               172060,
                                                               5,
                                                               172070,
                                                               172790,
                                                               6,
                                                               172800,
                                                               174810,
                                                               7,
                                                               174820,
                                                               176000
                                                           ]
                                          },
                                          {
                                              "verse_key":  "76:21",
                                              "timestamp_from":  176000,
                                              "timestamp_to":  193410,
                                              "duration":  17410,
                                              "segments":  [
                                                               1,
                                                               176030,
                                                               177120,
                                                               2,
                                                               177130,
                                                               177870,
                                                               3,
                                                               177880,
                                                               179450,
                                                               4,
                                                               179460,
                                                               180180,
                                                               5,
                                                               180190,
                                                               182830,
                                                               6,
                                                               182840,
                                                               185230,
                                                               7,
                                                               185240,
                                                               186210,
                                                               8,
                                                               186220,
                                                               186890,
                                                               9,
                                                               186900,
                                                               188520,
                                                               10,
                                                               188530,
                                                               189710,
                                                               11,
                                                               189720,
                                                               190630,
                                                               12,
                                                               190640,
                                                               191500,
                                                               13,
                                                               191510,
                                                               193410
                                                           ]
                                          },
                                          {
                                              "verse_key":  "76:22",
                                              "timestamp_from":  193410,
                                              "timestamp_to":  203680,
                                              "duration":  10270,
                                              "segments":  [
                                                               1,
                                                               193440,
                                                               194710,
                                                               2,
                                                               194720,
                                                               195450,
                                                               3,
                                                               195460,
                                                               196090,
                                                               4,
                                                               196100,
                                                               196620,
                                                               5,
                                                               196630,
                                                               199360,
                                                               6,
                                                               199370,
                                                               200740,
                                                               7,
                                                               200750,
                                                               202480,
                                                               8,
                                                               202490,
                                                               203680
                                                           ]
                                          },
                                          {
                                              "verse_key":  "76:23",
                                              "timestamp_from":  203680,
                                              "timestamp_to":  210240,
                                              "duration":  6560,
                                              "segments":  [
                                                               1,
                                                               203710,
                                                               204810,
                                                               2,
                                                               204820,
                                                               205410,
                                                               3,
                                                               205420,
                                                               206440,
                                                               4,
                                                               206450,
                                                               207270,
                                                               5,
                                                               207280,
                                                               208350,
                                                               6,
                                                               208360,
                                                               210240
                                                           ]
                                          },
                                          {
                                              "verse_key":  "76:24",
                                              "timestamp_from":  210240,
                                              "timestamp_to":  216660,
                                              "duration":  6420,
                                              "segments":  [
                                                               1,
                                                               210270,
                                                               210920,
                                                               2,
                                                               210930,
                                                               211600,
                                                               3,
                                                               211610,
                                                               212440,
                                                               4,
                                                               212450,
                                                               212940,
                                                               5,
                                                               212950,
                                                               213270,
                                                               6,
                                                               213280,
                                                               214310,
                                                               7,
                                                               214320,
                                                               215240,
                                                               8,
                                                               215250,
                                                               215540,
                                                               9,
                                                               215550,
                                                               216660
                                                           ]
                                          },
                                          {
                                              "verse_key":  "76:25",
                                              "timestamp_from":  216660,
                                              "timestamp_to":  221590,
                                              "duration":  4930,
                                              "segments":  [
                                                               1,
                                                               216690,
                                                               217300,
                                                               2,
                                                               217310,
                                                               217730,
                                                               3,
                                                               217740,
                                                               218520,
                                                               4,
                                                               218530,
                                                               219450,
                                                               5,
                                                               219460,
                                                               221590
                                                           ]
                                          },
                                          {
                                              "verse_key":  "76:26",
                                              "timestamp_from":  221590,
                                              "timestamp_to":  227770,
                                              "duration":  6180,
                                              "segments":  [
                                                               1,
                                                               221620,
                                                               222150,
                                                               2,
                                                               222160,
                                                               222850,
                                                               3,
                                                               222860,
                                                               223610,
                                                               4,
                                                               223620,
                                                               224170,
                                                               5,
                                                               224180,
                                                               225300,
                                                               6,
                                                               225310,
                                                               226000,
                                                               7,
                                                               226010,
                                                               227770
                                                           ]
                                          },
                                          {
                                              "verse_key":  "76:27",
                                              "timestamp_from":  227770,
                                              "timestamp_to":  241460,
                                              "duration":  13690,
                                              "segments":  [
                                                               1,
                                                               227800,
                                                               228950,
                                                               2,
                                                               228960,
                                                               232900,
                                                               3,
                                                               232910,
                                                               234040,
                                                               4,
                                                               234050,
                                                               235240,
                                                               5,
                                                               235250,
                                                               236380,
                                                               6,
                                                               236390,
                                                               239070,
                                                               7,
                                                               239080,
                                                               240420,
                                                               8,
                                                               240430,
                                                               241460
                                                           ]
                                          },
                                          {
                                              "verse_key":  "76:28",
                                              "timestamp_from":  241460,
                                              "timestamp_to":  254250,
                                              "duration":  12790,
                                              "segments":  [
                                                               1,
                                                               241510,
                                                               242000,
                                                               2,
                                                               242010,
                                                               243350,
                                                               3,
                                                               243360,
                                                               244140,
                                                               4,
                                                               244150,
                                                               247590,
                                                               5,
                                                               247600,
                                                               248330,
                                                               6,
                                                               248340,
                                                               249130,
                                                               7,
                                                               249140,
                                                               249940,
                                                               8,
                                                               249950,
                                                               253050,
                                                               9,
                                                               253060,
                                                               254250
                                                           ]
                                          },
                                          {
                                              "verse_key":  "76:29",
                                              "timestamp_from":  254250,
                                              "timestamp_to":  264260,
                                              "duration":  10010,
                                              "segments":  [
                                                               1,
                                                               254280,
                                                               255400,
                                                               2,
                                                               255410,
                                                               256390,
                                                               3,
                                                               256400,
                                                               257810,
                                                               4,
                                                               257820,
                                                               259020,
                                                               5,
                                                               259030,
                                                               260750,
                                                               6,
                                                               260760,
                                                               261670,
                                                               7,
                                                               261680,
                                                               262200,
                                                               8,
                                                               262210,
                                                               263140,
                                                               9,
                                                               263150,
                                                               264260
                                                           ]
                                          },
                                          {
                                              "verse_key":  "76:30",
                                              "timestamp_from":  264260,
                                              "timestamp_to":  279690,
                                              "duration":  15430,
                                              "segments":  [
                                                               1,
                                                               264290,
                                                               264820,
                                                               2,
                                                               264830,
                                                               267270,
                                                               3,
                                                               267280,
                                                               267750,
                                                               4,
                                                               267760,
                                                               270530,
                                                               5,
                                                               270540,
                                                               272960,
                                                               6,
                                                               272970,
                                                               275300,
                                                               7,
                                                               275310,
                                                               276240,
                                                               8,
                                                               276250,
                                                               276990,
                                                               9,
                                                               277000,
                                                               277560,
                                                               10,
                                                               277570,
                                                               278540,
                                                               11,
                                                               278550,
                                                               279690
                                                           ]
                                          },
                                          {
                                              "verse_key":  "76:31",
                                              "timestamp_from":  279690,
                                              "timestamp_to":  290940,
                                              "duration":  11250,
                                              "segments":  [
                                                               1,
                                                               279740,
                                                               280460,
                                                               2,
                                                               280470,
                                                               281410,
                                                               3,
                                                               281420,
                                                               283350,
                                                               4,
                                                               283360,
                                                               283720,
                                                               5,
                                                               283730,
                                                               285200,
                                                               6,
                                                               285210,
                                                               286920,
                                                               7,
                                                               286930,
                                                               287850,
                                                               8,
                                                               287860,
                                                               288470,
                                                               9,
                                                               288480,
                                                               289750,
                                                               10,
                                                               289760,
                                                               290940
                                                           ]
                                          }
                                      ]
                   }
}
